{
    "timestamp": "2025-07-12 14:30:03",
    "canvasXDimension": 500,
    "canvasYDimension": 500,
    "percentCovered": "32.86%",
    "updates": 85,
    "usersOnline": 190,
    "mostUsersOnline": 190,
    "mostUsersOnlineTime": "2025-07-12 14:30:03",
    "colors": [
        {
            "name": "Black",
            "className": "black",
            "count": 16124
        },
        {
            "name": "Blue",
            "className": "blue",
            "count": 6430
        },
        {
            "name": "Red",
            "className": "red",
            "count": 6108
        },
        {
            "name": "Yellow",
            "className": "yellow",
            "count": 5142
        },
        {
            "name": "Dark Green",
            "className": "dark-green",
            "count": 3499
        },
        {
            "name": "Dark Grey",
            "className": "dark-grey",
            "count": 2820
        },
        {
            "name": "Pink",
            "className": "pink",
            "count": 2687
        },
        {
            "name": "Aqua",
            "className": "aqua",
            "count": 2654
        },
        {
            "name": "Azure",
            "className": "azure",
            "count": 2590
        },
        {
            "name": "Dark Purple",
            "className": "dark-purple",
            "count": 2415
        },
        {
            "name": "Medium Grey",
            "className": "medium-grey",
            "count": 2295
        },
        {
            "name": "Deep Grey",
            "className": "deep-grey",
            "count": 2253
        },
        {
            "name": "Navy",
            "className": "navy",
            "count": 2237
        },
        {
            "name": "Purple",
            "className": "purple",
            "count": 2143
        },
        {
            "name": "Chocolate",
            "className": "chocolate",
            "count": 1863
        },
        {
            "name": "Beige",
            "className": "beige",
            "count": 1769
        },
        {
            "name": "Light Grey",
            "className": "light-grey",
            "count": 1741
        },
        {
            "name": "Rose",
            "className": "rose",
            "count": 1563
        },
        {
            "name": "Dark Teal",
            "className": "dark-teal",
            "count": 1455
        },
        {
            "name": "Dark Chocolate",
            "className": "dark-chocolate",
            "count": 1432
        },
        {
            "name": "Forest",
            "className": "forest",
            "count": 1356
        },
        {
            "name": "Orange",
            "className": "orange",
            "count": 1337
        },
        {
            "name": "Maroon",
            "className": "maroon",
            "count": 1313
        },
        {
            "name": "Brown",
            "className": "brown",
            "count": 1306
        },
        {
            "name": "Magenta",
            "className": "magenta",
            "count": 1257
        },
        {
            "name": "Watermelon",
            "className": "watermelon",
            "count": 929
        },
        {
            "name": "Lime",
            "className": "lime",
            "count": 907
        },
        {
            "name": "Peach",
            "className": "peach",
            "count": 890
        },
        {
            "name": "Light Teal",
            "className": "light-teal",
            "count": 837
        },
        {
            "name": "Green",
            "className": "green",
            "count": 826
        },
        {
            "name": "Rust",
            "className": "rust",
            "count": 776
        },
        {
            "name": "Pastel Yellow",
            "className": "pastel-yellow",
            "count": 707
        },
        {
            "name": "Mauve",
            "className": "mauve",
            "count": 477
        }
    ]
}