{
    "timestamp": "2025-07-13 12:10:04",
    "canvasXDimension": 500,
    "canvasYDimension": 500,
    "percentCovered": "75.02%",
    "updates": 215,
    "usersOnline": 202,
    "mostUsersOnline": 230,
    "mostUsersOnlineTime": "2025-07-12 17:00:03",
    "colors": [
        {
            "name": "Black",
            "className": "black",
            "count": 33317
        },
        {
            "name": "Blue",
            "className": "blue",
            "count": 13574
        },
        {
            "name": "Red",
            "className": "red",
            "count": 12730
        },
        {
            "name": "Yellow",
            "className": "yellow",
            "count": 11285
        },
        {
            "name": "Azure",
            "className": "azure",
            "count": 8674
        },
        {
            "name": "Medium Grey",
            "className": "medium-grey",
            "count": 7348
        },
        {
            "name": "Light Grey",
            "className": "light-grey",
            "count": 6937
        },
        {
            "name": "Dark Green",
            "className": "dark-green",
            "count": 6923
        },
        {
            "name": "Aqua",
            "className": "aqua",
            "count": 6415
        },
        {
            "name": "Dark Grey",
            "className": "dark-grey",
            "count": 6267
        },
        {
            "name": "Dark Purple",
            "className": "dark-purple",
            "count": 5879
        },
        {
            "name": "Navy",
            "className": "navy",
            "count": 5783
        },
        {
            "name": "Pink",
            "className": "pink",
            "count": 5455
        },
        {
            "name": "Deep Grey",
            "className": "deep-grey",
            "count": 5024
        },
        {
            "name": "Pastel Yellow",
            "className": "pastel-yellow",
            "count": 4546
        },
        {
            "name": "Purple",
            "className": "purple",
            "count": 4143
        },
        {
            "name": "Brown",
            "className": "brown",
            "count": 3874
        },
        {
            "name": "Dark Teal",
            "className": "dark-teal",
            "count": 3735
        },
        {
            "name": "Chocolate",
            "className": "chocolate",
            "count": 3526
        },
        {
            "name": "Rose",
            "className": "rose",
            "count": 3289
        },
        {
            "name": "Beige",
            "className": "beige",
            "count": 3266
        },
        {
            "name": "Magenta",
            "className": "magenta",
            "count": 2872
        },
        {
            "name": "Orange",
            "className": "orange",
            "count": 2798
        },
        {
            "name": "Rust",
            "className": "rust",
            "count": 2701
        },
        {
            "name": "Green",
            "className": "green",
            "count": 2518
        },
        {
            "name": "Dark Chocolate",
            "className": "dark-chocolate",
            "count": 2466
        },
        {
            "name": "Light Teal",
            "className": "light-teal",
            "count": 2324
        },
        {
            "name": "Peach",
            "className": "peach",
            "count": 1853
        },
        {
            "name": "Forest",
            "className": "forest",
            "count": 1713
        },
        {
            "name": "Maroon",
            "className": "maroon",
            "count": 1628
        },
        {
            "name": "Watermelon",
            "className": "watermelon",
            "count": 1623
        },
        {
            "name": "Lime",
            "className": "lime",
            "count": 1542
        },
        {
            "name": "Mauve",
            "className": "mauve",
            "count": 1531
        }
    ]
}