{
    "timestamp": "2025-07-12 16:00:03",
    "canvasXDimension": 500,
    "canvasYDimension": 500,
    "percentCovered": "37.78%",
    "updates": 94,
    "usersOnline": 208,
    "mostUsersOnline": 211,
    "mostUsersOnlineTime": "2025-07-12 15:50:03",
    "colors": [
        {
            "name": "Black",
            "className": "black",
            "count": 18021
        },
        {
            "name": "Blue",
            "className": "blue",
            "count": 7122
        },
        {
            "name": "Red",
            "className": "red",
            "count": 6826
        },
        {
            "name": "Yellow",
            "className": "yellow",
            "count": 6330
        },
        {
            "name": "Dark Green",
            "className": "dark-green",
            "count": 4151
        },
        {
            "name": "Pink",
            "className": "pink",
            "count": 3405
        },
        {
            "name": "Dark Grey",
            "className": "dark-grey",
            "count": 3141
        },
        {
            "name": "Aqua",
            "className": "aqua",
            "count": 3014
        },
        {
            "name": "Azure",
            "className": "azure",
            "count": 2996
        },
        {
            "name": "Dark Purple",
            "className": "dark-purple",
            "count": 2972
        },
        {
            "name": "Medium Grey",
            "className": "medium-grey",
            "count": 2921
        },
        {
            "name": "Navy",
            "className": "navy",
            "count": 2677
        },
        {
            "name": "Light Grey",
            "className": "light-grey",
            "count": 2546
        },
        {
            "name": "Deep Grey",
            "className": "deep-grey",
            "count": 2473
        },
        {
            "name": "Purple",
            "className": "purple",
            "count": 2324
        },
        {
            "name": "Chocolate",
            "className": "chocolate",
            "count": 2188
        },
        {
            "name": "Beige",
            "className": "beige",
            "count": 2110
        },
        {
            "name": "Rose",
            "className": "rose",
            "count": 1830
        },
        {
            "name": "Dark Teal",
            "className": "dark-teal",
            "count": 1663
        },
        {
            "name": "Orange",
            "className": "orange",
            "count": 1500
        },
        {
            "name": "Dark Chocolate",
            "className": "dark-chocolate",
            "count": 1494
        },
        {
            "name": "Forest",
            "className": "forest",
            "count": 1441
        },
        {
            "name": "Brown",
            "className": "brown",
            "count": 1407
        },
        {
            "name": "Magenta",
            "className": "magenta",
            "count": 1399
        },
        {
            "name": "Maroon",
            "className": "maroon",
            "count": 1360
        },
        {
            "name": "Rust",
            "className": "rust",
            "count": 1040
        },
        {
            "name": "Watermelon",
            "className": "watermelon",
            "count": 988
        },
        {
            "name": "Green",
            "className": "green",
            "count": 974
        },
        {
            "name": "Lime",
            "className": "lime",
            "count": 939
        },
        {
            "name": "Light Teal",
            "className": "light-teal",
            "count": 931
        },
        {
            "name": "Peach",
            "className": "peach",
            "count": 914
        },
        {
            "name": "Pastel Yellow",
            "className": "pastel-yellow",
            "count": 871
        },
        {
            "name": "Mauve",
            "className": "mauve",
            "count": 494
        }
    ]
}