{
    "timestamp": "2025-07-12 07:20:03",
    "canvasXDimension": 500,
    "canvasYDimension": 500,
    "percentCovered": "12.87%",
    "updates": 43,
    "usersOnline": 153,
    "mostUsersOnline": 155,
    "mostUsersOnlineTime": "2025-07-12 07:10:03",
    "colors": [
        {
            "name": "Black",
            "className": "black",
            "count": 7988
        },
        {
            "name": "Blue",
            "className": "blue",
            "count": 2469
        },
        {
            "name": "Red",
            "className": "red",
            "count": 1789
        },
        {
            "name": "Dark Green",
            "className": "dark-green",
            "count": 1690
        },
        {
            "name": "Yellow",
            "className": "yellow",
            "count": 1667
        },
        {
            "name": "Dark Grey",
            "className": "dark-grey",
            "count": 1596
        },
        {
            "name": "Navy",
            "className": "navy",
            "count": 1379
        },
        {
            "name": "Dark Purple",
            "className": "dark-purple",
            "count": 1159
        },
        {
            "name": "Deep Grey",
            "className": "deep-grey",
            "count": 938
        },
        {
            "name": "Medium Grey",
            "className": "medium-grey",
            "count": 919
        },
        {
            "name": "Orange",
            "className": "orange",
            "count": 886
        },
        {
            "name": "Azure",
            "className": "azure",
            "count": 794
        },
        {
            "name": "Pink",
            "className": "pink",
            "count": 793
        },
        {
            "name": "Dark Teal",
            "className": "dark-teal",
            "count": 736
        },
        {
            "name": "Aqua",
            "className": "aqua",
            "count": 716
        },
        {
            "name": "Dark Chocolate",
            "className": "dark-chocolate",
            "count": 632
        },
        {
            "name": "Light Grey",
            "className": "light-grey",
            "count": 586
        },
        {
            "name": "Chocolate",
            "className": "chocolate",
            "count": 534
        },
        {
            "name": "Beige",
            "className": "beige",
            "count": 525
        },
        {
            "name": "Purple",
            "className": "purple",
            "count": 509
        },
        {
            "name": "Forest",
            "className": "forest",
            "count": 471
        },
        {
            "name": "Brown",
            "className": "brown",
            "count": 456
        },
        {
            "name": "Rust",
            "className": "rust",
            "count": 412
        },
        {
            "name": "Rose",
            "className": "rose",
            "count": 410
        },
        {
            "name": "Magenta",
            "className": "magenta",
            "count": 402
        },
        {
            "name": "Maroon",
            "className": "maroon",
            "count": 295
        },
        {
            "name": "Pastel Yellow",
            "className": "pastel-yellow",
            "count": 273
        },
        {
            "name": "Light Teal",
            "className": "light-teal",
            "count": 258
        },
        {
            "name": "Green",
            "className": "green",
            "count": 228
        },
        {
            "name": "Watermelon",
            "className": "watermelon",
            "count": 225
        },
        {
            "name": "Lime",
            "className": "lime",
            "count": 191
        },
        {
            "name": "Peach",
            "className": "peach",
            "count": 182
        },
        {
            "name": "Mauve",
            "className": "mauve",
            "count": 59
        }
    ]
}